Metadata-Version: 2.1
Name: matcha-tts
Version: 0.0.7.2
Summary: 🍵 Matcha-TTS: A fast TTS architecture with conditional flow matching
Home-page: https://shivammehta25.github.io/Matcha-TTS
Author: Shivam Mehta
Author-email: shivam.mehta25@gmail.com
Requires-Python: >=3.9.0
License-File: LICENSE
Requires-Dist: torch >=2.0.0
Requires-Dist: torchvision >=0.15.0
Requires-Dist: lightning >=2.0.0
Requires-Dist: torchmetrics >=0.11.4
Requires-Dist: hydra-core ==1.3.2
Requires-Dist: hydra-colorlog ==1.2.0
Requires-Dist: hydra-optuna-sweeper ==1.2.0
Requires-Dist: rootutils
Requires-Dist: pre-commit
Requires-Dist: rich
Requires-Dist: pytest
Requires-Dist: phonemizer
Requires-Dist: tensorboard
Requires-Dist: librosa
Requires-Dist: Cython
Requires-Dist: numpy
Requires-Dist: einops
Requires-Dist: inflect
Requires-Dist: Unidecode
Requires-Dist: scipy
Requires-Dist: torchaudio
Requires-Dist: matplotlib
Requires-Dist: pandas
Requires-Dist: conformer ==0.3.2
Requires-Dist: diffusers
Requires-Dist: notebook
Requires-Dist: ipywidgets
Requires-Dist: gradio ==3.43.2
Requires-Dist: gdown
Requires-Dist: wget
Requires-Dist: seaborn
